[
  {
    "label": "=============== HCM - Quận 4 ===============",
    "options": [{ "label": "346 Bến Vân Đồn", "id": "346 Bến Vân Đồn}" }]
  },
  {
    "label": "=============== HCM - Quận 1 ===============",
    "options": [
      { "label": "213 Nguyễn Cư Trinh", "id": "213 Nguyễn Cư Trinh}" },
      { "label": "20 Trần Cao Vân", "id": "20 Trần Cao Vân}" },
      { "label": "57 Trần Hưng Đạo", "id": "57 Trần Hưng Đạo}" },
      { "label": "166 Nguyễn Công Trứ", "id": "166 Nguyễn Công Trứ}" },
      { "label": "81 Mạc Thị Bưởi", "id": "81 Mạc Thị Bưởi}" },
      { "label": "110 Nam Kỳ Khởi Nghĩa", "id": "110 Nam Kỳ Khởi Nghĩa}" },
      { "label": "08 Nguyễn Trãi", "id": "08 Nguyễn Trãi}" }
    ]
  },
  {
    "label": "=============== HCM - Quận 3 ===============",
    "options": [
      { "label": "46 Võ Văn Tần", "id": "46 Võ Văn Tần}" },
      { "label": "19 Cao Thắng, Phường 2", "id": "19 Cao Thắng, Phường 2}" },
      { "label": "42 Trần Cao Vân", "id": "42 Trần Cao Vân}" },
      { "label": "61 Bà Huyện Thanh Quan", "id": "61 Bà Huyện Thanh Quan}" }
    ]
  },
  {
    "label": "=============== HCM - Quận 7 ===============",
    "options": [
      { "label": "Crescrnt Mall", "id": "Crescrnt Mall}" },
      { "label": "Tầng 1 SC Vivo City", "id": "Tầng 1 SC Vivo City}" },
      { "label": "99 Nguyễn Thị Thập", "id": "99 Nguyễn Thị Thập}" }
    ]
  },
  {
    "label": "=============== HCM - Bình Chánh ===============",
    "options": [{ "label": "Chung cư MIA", "id": "Chung cư MIA}" }]
  },
  {
    "label": "=============== HCM - Quận 10 ===============",
    "options": [
      { "label": "Tầng 1 Vạn Hạnh Mall", "id": "Tầng 1 Vạn Hạnh Mall}" },
      { "label": "213 Ba Tháng Hai", "id": "213 Ba Tháng Hai}" }
    ]
  },
  {
    "label": "=============== HCM - Quận 5 ===============",
    "options": [
      { "label": "391A An Dương Vương", "id": "391A An Dương Vương}" }
    ]
  },
  {
    "label": "=============== HCM - Quận 2 ===============",
    "options": [
      { "label": "14T Xuân Thủy", "id": "14T Xuân Thủy}" },
      { "label": "28 Mai Chí Thọ", "id": "28 Mai Chí Thọ}" }
    ]
  },
  {
    "label": "=============== HCM - Quận Thủ Đức ===============",
    "options": [{ "label": "Tầng 4, Giga Mall", "id": "Tầng 4, Giga Mall}" }]
  },
  {
    "label": "=============== HCM - Quận Bình Thạnh ===============",
    "options": [
      { "label": "188 Nguyễn Xí", "id": "188 Nguyễn Xí}" },
      { "label": "238 Phan Xích Long", "id": "238 Phan Xích Long}" }
    ]
  },
  {
    "label": "=============== HCM - Quận Tân Phú ===============",
    "options": [
      { "label": "278 Hòa Bình", "id": "278 Hòa Bình}" },
      { "label": "212 Thoại Ngọc Hầu", "id": "212 Thoại Ngọc Hầu}" }
    ]
  },
  {
    "label": "=============== HCM - Quận Tân Bình ===============",
    "options": [
      { "label": "93 Trần Quốc Hoàn", "id": "93 Trần Quốc Hoàn}" },
      { "label": "132 Hoàng Hoa Thám", "id": "132 Hoàng Hoa Thám}" },
      { "label": "315 Hoàng Văn Thụ", "id": "315 Hoàng Văn Thụ}" },
      { "label": "960 Âu Cơ", "id": "960 Âu Cơ}" }
    ]
  },
  {
    "label": "=============== HCM - Quận 12 ===============",
    "options": [{ "label": "Mega Hiệp Phú", "id": "Mega Hiệp Phú}" }]
  },
  {
    "label": "=============== HCM - Quận Gò Vấp ===============",
    "options": [{ "label": "487 Phan Văn Trị", "id": "487 Phan Văn Trị}" }]
  },
  {
    "label": "=============== Đồng Nai - Biên Hòa ===============",
    "options": [
      { "label": "170 đường 30/04", "id": "170 đường 30/04}" },
      { "label": "1135 Đ. Nguyễn Ái Quốc", "id": "1135 Đ. Nguyễn Ái Quốc}" },
      {
        "label": "Tầng 2, Tòa nhà 121 Phạm Văn Thuận",
        "id": "Tầng 2, Tòa nhà 121 Phạm Văn Thuận}"
      }
    ]
  }
]
